{
    "test_time": "2025/02/11",
    "flows": [
        {
            "flow_name": "supir_upscaler",
            "flow_display_name": "SUPIR Upscaler",
            "test_cases": [
                {
                    "test_case": "1024x1024 - 2x scaling",
                    "vram_state": "NORMAL_VRAM",
                    "disable_smart_memory": false,
                    "avg_exec_time": 193.73355600700006,
                    "avg_max_memory_usage": 8604.96
                },
                {
                    "test_case": "1024x1024 - 2x scaling",
                    "vram_state": "NORMAL_VRAM",
                    "disable_smart_memory": true,
                    "avg_exec_time": 195.92801903750023,
                    "avg_max_memory_usage": 9402.45
                },
                {
                    "test_case": "1024x1024 - 1.5x scaling",
                    "vram_state": "NORMAL_VRAM",
                    "disable_smart_memory": false,
                    "avg_exec_time": 92.15345877100026,
                    "avg_max_memory_usage": 8601.03
                },
                {
                    "test_case": "1024x1024 - 1.5x scaling",
                    "vram_state": "NORMAL_VRAM",
                    "disable_smart_memory": true,
                    "avg_exec_time": 92.7505675880002,
                    "avg_max_memory_usage": 9398.51
                }
            ]
        }
    ]
}
