{
  "name": "mobius_xl",
  "display_name": "Mobius XL",
  "description": "Mobius XL model",
  "author": "bigcat88",
  "homepage": "https://github.com/bigcat88",
  "license": "",
  "documentation": "https://visionatrix.github.io/VixFlowsDocs/Flows/Mobius_XL.html",
  "input_params": [
    {
      "name": "prompt",
      "display_name": "Prompt",
      "type": "text",
      "optional": false,
      "comfy_node_id": {
        "243": {
          "dest_field_name": [
            "inputs",
            "text"
          ]
        }
      }
    },
    {
      "name": "negative_prompt",
      "display_name": "Negative Prompt",
      "type": "text",
      "optional": true,
      "advanced": true,
      "comfy_node_id": {
        "242": {
          "dest_field_name": [
            "inputs",
            "text"
          ]
        }
      }
    },
    {
      "name": "fast_run",
      "display_name": "Fast run",
      "type": "bool",
      "default": false,
      "optional": true,
      "advanced": true,
      "comfy_node_id": {
        "267": {
          "dest_field_name": [
            "inputs",
            "images"
          ],
          "value": [
            "275",
            0
          ]
        }
      }
    },
    {
      "name": "prompt_strength",
      "display_name": "Prompt strength",
      "type": "range",
      "optional": true,
      "advanced": true,
      "default": 5.0,
      "min": 3.5,
      "max": 7.0,
      "step": 0.1,
      "comfy_node_id": {
        "27": {
          "dest_field_name": [
            "inputs",
            "cfg"
          ],
          "internal_type": "float"
        },
        "268": {
          "dest_field_name": [
            "inputs",
            "cfg"
          ],
          "internal_type": "float"
        }
      }
    }
  ]
}